solc_select/__init__.py
solc_select/__main__.py
solc_select/constants.py
solc_select/solc_select.py
solc_select/utils.py
solc_select-1.0.4.dist-info/LICENSE
solc_select-1.0.4.dist-info/METADATA
solc_select-1.0.4.dist-info/WHEEL
solc_select-1.0.4.dist-info/entry_points.txt
solc_select-1.0.4.dist-info/top_level.txt
solc_select-1.0.4.dist-info/RECORD
