Metadata-Version: 2.1
Name: solc-select
Version: 1.0.4
Summary: Manage multiple Solidity compiler versions.
Home-page: https://github.com/crytic/solc-select
Author: Trail of Bits
License: AGPL-3.0
Requires-Python: >=3.6
License-File: LICENSE
